{
  "placements": {
    "campfire_circle": {
      "gridPosition": {
        "x": 15,
        "y": 21
      },
      "footprint": {
        "w": 4,
        "h": 4
      }
    },
    "calm_beach": {
      "gridPosition": {
        "x": 5,
        "y": 31
      },
      "footprint": {
        "w": 6,
        "h": 4
      }
    },
    "welcome_dock": {
      "gridPosition": {
        "x": 43,
        "y": 37
      },
      "footprint": {
        "w": 6,
        "h": 4
      }
    },
    "art_hut": {
      "gridPosition": {
        "x": 28,
        "y": 20
      },
      "footprint": {
        "w": 4,
        "h": 4
      }
    },
    "arcade_cove": {
      "gridPosition": {
        "x": 42,
        "y": 24
      },
      "footprint": {
        "w": 5,
        "h": 4
      }
    },
    "treehouse_hideaway": {
      "gridPosition": {
        "x": 4,
        "y": 20
      },
      "footprint": {
        "w": 5,
        "h": 5
      }
    },
    "lighthouse_point": {
      "gridPosition": {
        "x": 30,
        "y": 4
      },
      "footprint": {
        "w": 4,
        "h": 4
      }
    }
  },
  "spawn": {
    "x": 44,
    "y": 33
  }
}